tap_businesscentral/__init__.py
tap_businesscentral/discover.py
tap_businesscentral/sync.py
tap_businesscentral/schemas/sample_stream.json
tap_businesscentral-0.1.2.dist-info/LICENSE
tap_businesscentral-0.1.2.dist-info/METADATA
tap_businesscentral-0.1.2.dist-info/WHEEL
tap_businesscentral-0.1.2.dist-info/dependency_links.txt
tap_businesscentral-0.1.2.dist-info/entry_points.txt
tap_businesscentral-0.1.2.dist-info/top_level.txt
tap_businesscentral-0.1.2.dist-info/RECORD
