Metadata-Version: 2.1
Name: tap-businesscentral
Version: 0.1.2
Summary: Singer.io tap for extracting data
Home-page: http://singer.io
Author: Stitch
Author-email: UNKNOWN
License: UNKNOWN
Platform: UNKNOWN
Classifier: Programming Language :: Python :: 3 :: Only
Requires-Dist: singer-python (>=5.0.12)
Requires-Dist: requests
Requires-Dist: odata
